{
  "https://grand-collapse.bandcamp.com/album/along-the-dew": "paid",
  "https://cyanidethrash.bandcamp.com/album/world-peace-six-feet-under": "paid",
  "https://eruptionthrash.bandcamp.com/album/cloaks-of-oblivion": "paid",
  "https://xenophile.bandcamp.com/album/systematic-enslavement": "paid",
  "https://pizzatramp.bandcamp.com/album/revenge-of-the-bangertronic-dan": "paid",
  "https://hellbringer.bandcamp.com/album/dominion-of-darkness": "paid",
  "https://fatalagent.bandcamp.com/album/demo-lition": "paid",
  "https://deathsquadthrash.bandcamp.com/album/split-you-at-the-seams": "paid",
  "https://neardeathcle.bandcamp.com/album/2016-promo": {
    "url": "https://neardeathcle.bandcamp.com/album/2016-promo",
    "title": "2016 Promo",
    "artist": "Near Death",
    "imageUrl": "https://f4.bcbits.com/img/a0629943614_16.jpg",
    "embedId": "885142655"
  },
  "https://deadcross.bandcamp.com/album/dead-cross": "paid",
  "https://thevirus.bandcamp.com/album/system-failure": "paid",
  "https://selfharm780.bandcamp.com/album/yanluo": {
    "url": "https://selfharm780.bandcamp.com/album/yanluo",
    "title": "Yanluo",
    "artist": "Self Harm",
    "imageUrl": "https://f4.bcbits.com/img/a3962851040_16.jpg",
    "embedId": "361846778"
  },
  "https://midnight-ohio.bandcamp.com/album/shox-of-violence": "paid",
  "https://violatorthrash.bandcamp.com/album/violent-mosh": "paid",
  "https://stillalive.bandcamp.com/album/trials": {
    "url": "https://stillalive.bandcamp.com/album/trials",
    "title": "Trials",
    "artist": "Still Alive",
    "imageUrl": "https://f4.bcbits.com/img/a2946391789_16.jpg",
    "embedId": "360123123"
  },
  "https://candlelightrecordsuk.bandcamp.com/album/my-arms-your-hearse": "paid",
  "https://violatorthrash.bandcamp.com/album/annihilation-process": "paid",
  "https://candlelightrecordsuk.bandcamp.com/album/passion": "paid",
  "https://shortleashhc.bandcamp.com/album/ball-and-chain": {
    "url": "https://shortleashhc.bandcamp.com/album/ball-and-chain",
    "title": "Ball and Chain",
    "artist": "Short Leash",
    "imageUrl": "https://f4.bcbits.com/img/a3594440735_16.jpg",
    "embedId": "1311774688"
  },
  "https://osmoseproductions.bandcamp.com/album/triumph-genocide-antichrist": "paid",
  "https://a389recordings.bandcamp.com/album/noisem-occultist-slaugher-of-the-innocent-and-the-damned-split": "paid",
  "https://candlelightrecordsuk.bandcamp.com/album/das-seelenbrechen": "paid",
  "https://kisses.bandcamp.com/album/kids-in-la": "paid",
  "https://violatorthrash.bandcamp.com/album/chemical-assault-2": "paid",
  "https://borisrecords.bandcamp.com/album/soul-rot-cd": "paid",
  "https://decomposermn.bandcamp.com/album/relapse": "paid",
  "https://radostimoja.bandcamp.com/album/tmx": "paid",
  "https://closedcasketactivities.bandcamp.com/album/born-into-debt-we-all-owe-a-death": "paid",
  "https://pitboss2000.bandcamp.com/album/the-overview-effect": "paid",
  "https://stillalive.bandcamp.com/album/choices": "paid",
  "https://borisrecords.bandcamp.com/album/gunpowder-gray-12": "paid",
  "https://nunslaughter.bandcamp.com/album/hells-unholy-fire": "paid",
  "https://skyshadowobelisk.bandcamp.com/album/the-gift-of-light": "paid",
  "https://skulled.bandcamp.com/album/chaos-through-order": "paid",
  "https://osmoseproductions.bandcamp.com/album/exterminate": "paid",
  "https://nofealty.bandcamp.com/album/in-the-shadow-of-the-monolith": {
    "url": "https://nofealty.bandcamp.com/album/in-the-shadow-of-the-monolith",
    "title": "In the Shadow of the Monolith",
    "artist": "NO FEALTY",
    "imageUrl": "https://f4.bcbits.com/img/a1594094872_16.jpg",
    "embedId": "3552714444"
  },
  "https://momanddad.bandcamp.com/album/i-am-therefore-i-is": "paid",
  "https://osmoseproductions.bandcamp.com/album/scum-collapse-eradication": "paid",
  "https://verbalrazors.bandcamp.com/album/misleading-innocence": "paid",
  "https://pitboss2000.bandcamp.com/album/the-cult-of-fuck-yeah": "paid",
  "https://hypertension.bandcamp.com/album/dark-storms-arise": "paid",
  "https://instructor.bandcamp.com/album/instructor": "paid",
  "https://darksister.bandcamp.com/album/darkest-lipstick-in-the-drugstore": "paid",
  "https://frameofmindhc.bandcamp.com/album/frame-of-mind": {
    "url": "https://frameofmindhc.bandcamp.com/album/frame-of-mind",
    "title": "Frame of Mind",
    "artist": "Frame of Mind",
    "imageUrl": "https://f4.bcbits.com/img/a2060452569_16.jpg",
    "embedId": "3447379002"
  },
  "https://relapsealumni.bandcamp.com/album/surrounded-by-thieves": "paid",
  "https://ahanging504.bandcamp.com/album/house-of-goats-vs-a-hanging-thrash-fight": {
    "url": "https://ahanging504.bandcamp.com/album/house-of-goats-vs-a-hanging-thrash-fight",
    "title": "House Of Goats vs. A Hanging: THRASH FIGHT​!​!​!",
    "artist": "House Of Goats/A Hanging",
    "imageUrl": "https://f4.bcbits.com/img/a4084624861_16.jpg",
    "embedId": "2526816633"
  },
  "https://borisrecords.bandcamp.com/album/exegesis-12ep": "paid",
  "https://bastardsect.bandcamp.com/album/they-want-a-war": "paid",
  "https://osmoseproductions.bandcamp.com/album/de-principii-evangelikum": "paid",
  "https://iscariotny.bandcamp.com/album/blood-doctrines": "paid",
  "https://destruktor.bandcamp.com/album/opprobrium": "paid",
  "https://propagandhi.bandcamp.com/album/todays-empires-tomorrows-ashes": "paid",
  "https://osmoseproductions.bandcamp.com/album/those-of-the-unlight": "paid",
  "https://candlelightrecordsuk.bandcamp.com/album/the-virus-conspires": "paid",
  "https://risingbeast.bandcamp.com/album/ligeia": {
    "url": "https://risingbeast.bandcamp.com/album/ligeia",
    "title": "Ligeia",
    "artist": "MOONKNIGHT",
    "imageUrl": "https://f4.bcbits.com/img/a1204695312_16.jpg",
    "embedId": "583269802"
  },
  "https://skinfather.bandcamp.com/album/none-will-mourn": "paid",
  "https://inimical.bandcamp.com/album/whorehouse-of-representatives-discography": "paid",
  "https://americanx.bandcamp.com/album/coping-with-loss": {
    "url": "https://americanx.bandcamp.com/album/coping-with-loss",
    "title": "Coping With Loss",
    "artist": "american",
    "imageUrl": "https://f4.bcbits.com/img/a3034801163_16.jpg",
    "embedId": "1254127012"
  },
  "https://allouthelter.bandcamp.com/album/manifesto": "paid",
  "https://nunslaughter.bandcamp.com/album/goat": "paid",
  "https://borisrecords.bandcamp.com/album/wicca-7": "paid",
  "https://humansoundsrecords.bandcamp.com/album/groups": {
    "url": "https://humansoundsrecords.bandcamp.com/album/groups",
    "title": "groups",
    "artist": "acab rocky",
    "imageUrl": "https://f4.bcbits.com/img/a2427234556_16.jpg",
    "embedId": "3272776339"
  },
  "https://osmoseproductions.bandcamp.com/album/rest-in-peace": "paid",
  "https://osmoseproductions.bandcamp.com/album/total-inferno": "paid",
  "https://osmoseproductions.bandcamp.com/album/the-inexorable": "paid",
  "https://foreseen.bandcamp.com/album/power-intoxication-b-w-dying-spirit": "paid",
  "https://seanceca.bandcamp.com/album/introspection-2": {
    "url": "https://seanceca.bandcamp.com/album/introspection-2",
    "title": "Introspection",
    "artist": "Seance",
    "imageUrl": "https://f4.bcbits.com/img/a1452861895_16.jpg",
    "embedId": "2223417741"
  },
  "https://snorlax666.bandcamp.com/album/wingpuller": {
    "url": "https://snorlax666.bandcamp.com/album/wingpuller",
    "title": "Wingpuller",
    "artist": "SNORLAX",
    "imageUrl": "https://f4.bcbits.com/img/a1132805652_16.jpg",
    "embedId": "3788768761"
  },
  "https://zegemabeachrecords.bandcamp.com/album/tetola93": "paid",
  "https://candlelightrecordsuk.bandcamp.com/album/graveward": "paid",
  "https://blastasfuk.bandcamp.com/album/divided-we-fall": "paid",
  "https://herdmover.bandcamp.com/album/vol-2-rural-banishment": {
    "url": "https://herdmover.bandcamp.com/album/vol-2-rural-banishment",
    "title": "Vol. 2: Rural Banishment",
    "artist": "Herd Mover",
    "imageUrl": "https://f4.bcbits.com/img/a1164987017_16.jpg",
    "embedId": "3097995290"
  },
  "https://borisrecords.bandcamp.com/album/hellish-mercenary-7": "paid",
  "https://blastasfuk.bandcamp.com/album/expression-of-pain": "paid",
  "https://rehashed.bandcamp.com/album/demo-2008": "paid",
  "https://gouge-norway.bandcamp.com/album/doomed-to-death-2": "paid",
  "https://osmoseproductions.bandcamp.com/album/emissaries": "paid",
  "https://deadyetband.bandcamp.com/album/this-cities-child": {
    "url": "https://deadyetband.bandcamp.com/album/this-cities-child",
    "title": "This Cities Child",
    "artist": "Deadyet?",
    "imageUrl": "https://f4.bcbits.com/img/a1774433079_16.jpg",
    "embedId": "3567756918"
  },
  "https://sidetracked.bandcamp.com/album/self-inflicted-split": {
    "url": "https://sidetracked.bandcamp.com/album/self-inflicted-split",
    "title": "Self Inflicted split",
    "artist": "Sidetracked",
    "imageUrl": "https://f4.bcbits.com/img/a0194691926_16.jpg",
    "embedId": "4009692703"
  },
  "https://borisrecords.bandcamp.com/album/eden-in-flames-7": "paid",
  "https://worldsucks.bandcamp.com/album/warning-you-with-peace-love": "paid",
  "https://insurgencythrashuk.bandcamp.com/album/death-march": "paid",
  "https://osmoseproductions.bandcamp.com/album/sur-les-falaises-de-marbre": "paid",
  "https://bastard666.bandcamp.com/album/hades-command": "paid",
  "https://hypertension.bandcamp.com/album/primeval-tyrants-prevails": "paid",
  "https://borisrecords.bandcamp.com/album/involuntary-organ-donor-7": "paid",
  "https://selfharm780.bandcamp.com/album/self-harm-x-wvrm-split-2016": {
    "url": "https://selfharm780.bandcamp.com/album/self-harm-x-wvrm-split-2016",
    "title": "Self Harm x WVRM Split 2016",
    "artist": "Self Harm",
    "imageUrl": "https://f4.bcbits.com/img/a2198155752_16.jpg",
    "embedId": "4006110797"
  },
  "https://excelsl.bandcamp.com/album/split-image": "paid",
  "https://boids.bandcamp.com/album/superbafrango": "paid",
  "https://reignoffury.bandcamp.com/album/death-be-thy-shepherd": "paid",
  "https://relapsealumni.bandcamp.com/album/suffocation": "paid",
  "https://ltcp.bandcamp.com/album/nemesis-ablaze": "paid",
  "https://nunslaughter.bandcamp.com/album/angelic-dread": "paid",
  "https://nylithia.bandcamp.com/album/infector-ep": "paid",
  "https://bastard666.bandcamp.com/album/alcoholocaust-ep": "paid",
  "https://minusyouth.bandcamp.com/album/teenage-duty": {
    "url": "https://minusyouth.bandcamp.com/album/teenage-duty",
    "title": "Teenage Duty",
    "artist": "MINUS YOUTH",
    "imageUrl": "https://f4.bcbits.com/img/a1428575012_16.jpg",
    "embedId": "688106224"
  },
  "https://violatorthrash.bandcamp.com/album/scenarios-of-brutality": "paid",
  "https://possessionproductions.bandcamp.com/album/bloodrain-v-adora-satanae": {
    "url": "https://possessionproductions.bandcamp.com/album/bloodrain-v-adora-satanae",
    "title": "Bloodrain V: Adora Satanae",
    "artist": "Bloodrain",
    "imageUrl": "https://f4.bcbits.com/img/a0403901258_16.jpg",
    "embedId": "4183486844"
  },
  "https://rehashed.bandcamp.com/album/code-black": "paid",
  "https://a389recordings.bandcamp.com/album/noisem-blossoming-decay": "paid",
  "https://vornth.bandcamp.com/album/vornth": "paid",
  "https://evilempire.bandcamp.com/album/does-this-genocide-make-me-look-sexy": "paid",
  "https://nequient.bandcamp.com/album/infinite-regress-2": "paid",
  "https://elguitartom.bandcamp.com/album/knee-deep-in-metal-remastered": "paid",
  "https://430steps.bandcamp.com/album/faster-louder": "paid",
  "https://abysmal-lord.bandcamp.com/album/storms-of-unholy-black-mass": "paid",
  "https://disterror.bandcamp.com/album/catharsis": "paid",
  "https://frontierrecords-suicidaltendencies.bandcamp.com/album/suicidal-tendencies": "paid",
  "https://candlelightrecordsuk.bandcamp.com/album/in-the-constellation-of-the-black-widow": "paid",
  "https://closedcasketactivities.bandcamp.com/album/split-4": "paid",
  "https://bumfeeder.bandcamp.com/album/cloaked-in-vomit": {
    "url": "https://bumfeeder.bandcamp.com/album/cloaked-in-vomit",
    "title": "CLOAKED IN VOMIT",
    "artist": "BUMFEEDER",
    "imageUrl": "https://f4.bcbits.com/img/a2324561188_16.jpg",
    "embedId": "2821682226"
  },
  "https://sick-tired.bandcamp.com/album/split-12-w-triac": "paid",
  "https://deathblow1.bandcamp.com/album/demolition-deployment": "paid",
  "https://borisrecords.bandcamp.com/album/end-of-man-7": "paid",
  "https://insist.bandcamp.com/album/demo": {
    "url": "https://insist.bandcamp.com/album/demo",
    "title": "DEMO",
    "artist": "INSIST",
    "imageUrl": "https://f4.bcbits.com/img/a3108537920_16.jpg",
    "embedId": "1051605208"
  },
  "https://borisrecords.bandcamp.com/album/a-filthy-orgy-of-horror-and-death-12": "paid",
  "https://nightofthelivingshred.bandcamp.com/album/aint-nuthin-to-fuck-with": "paid",
  "https://elguitartom.bandcamp.com/album/egt-doom-covers-remastered": "paid",
  "https://danielwaxoff.bandcamp.com/album/split-with-the-fastplants": "paid",
  "https://propagandhi.bandcamp.com/album/how-to-clean-everything-20th-anniversary-edition": "paid",
  "https://pearstheband.bandcamp.com/album/letters-to-memaw": "paid",
  "https://osmoseproductions.bandcamp.com/album/below-the-lights": "paid",
  "https://relapsealumni.bandcamp.com/album/human-waste": "paid",
  "https://osmoseproductions.bandcamp.com/album/krigsmakt-mini-lp": "paid",
  "https://ringworm.bandcamp.com/album/the-promise": "paid",
  "https://nunslaughter.bandcamp.com/album/the-devils-congeries-volume-2": "paid",
  "https://profanatica-us.bandcamp.com/album/the-curling-flame-of-blasphemy": "paid",
  "https://sidetracked.bandcamp.com/album/opposition": {
    "url": "https://sidetracked.bandcamp.com/album/opposition",
    "title": "Opposition",
    "artist": "Sidetracked",
    "imageUrl": "https://f4.bcbits.com/img/a2385597007_16.jpg",
    "embedId": "864587417"
  },
  "https://blackmass708.bandcamp.com/album/sal-y-sangre": {
    "url": "https://blackmass708.bandcamp.com/album/sal-y-sangre",
    "title": "Sal y Sangre",
    "artist": "Black Mass",
    "imageUrl": "https://f4.bcbits.com/img/a3325620184_16.jpg",
    "embedId": "3424753805"
  },
  "https://evenworsenyc.bandcamp.com/album/we-suck-the-lost-album-aka-youve-ruined-everything": "paid",
  "https://invocationspells.bandcamp.com/album/the-flame-of-hate": "paid",
  "https://adhere.bandcamp.com/album/light-pollution": {
    "url": "https://adhere.bandcamp.com/album/light-pollution",
    "title": "Light Pollution",
    "artist": "Adhere",
    "imageUrl": "https://f4.bcbits.com/img/a2146298292_16.jpg",
    "embedId": "1394767077"
  },
  "https://gloompit.bandcamp.com/album/split": "paid",
  "https://relapsealumni.bandcamp.com/album/death-is-this-communion": "paid",
  "https://grizzlordestroys.bandcamp.com/album/grizzlor-godstopper-split-7": "paid",
  "https://sidetracked.bandcamp.com/album/forfeit": {
    "url": "https://sidetracked.bandcamp.com/album/forfeit",
    "title": "Forfeit",
    "artist": "Sidetracked",
    "imageUrl": "https://f4.bcbits.com/img/a0146504158_16.jpg",
    "embedId": "74958369"
  },
  "https://moths.bandcamp.com/album/freshdirt": {
    "url": "https://moths.bandcamp.com/album/freshdirt",
    "title": "FRESHDIRT",
    "artist": "MOTHS",
    "imageUrl": "https://f4.bcbits.com/img/a3345249619_16.jpg",
    "embedId": "3582880012"
  },
  "https://osmoseproductions.bandcamp.com/album/monumension": "paid",
  "https://reproach.bandcamp.com/album/is-what-it-is-e-p": {
    "url": "https://reproach.bandcamp.com/album/is-what-it-is-e-p",
    "title": "IS WHAT IT IS E​.​P.",
    "artist": "Reproach",
    "imageUrl": "https://f4.bcbits.com/img/a0761142877_16.jpg",
    "embedId": "174218640"
  },
  "https://homewreckeroh.bandcamp.com/album/worms-dirt": "paid",
  "https://relapsealumni.bandcamp.com/album/blessed-black-wings": "paid",
  "https://barbarian-italy.bandcamp.com/album/barbarian": "paid",
  "https://osmoseproductions.bandcamp.com/album/thill-smitts-terror": "paid",
  "https://excelsl.bandcamp.com/album/the-jokes-on-you": "paid",
  "https://denouncementpyre.bandcamp.com/album/black-sun-unbound": "paid",
  "https://crossjointhc.bandcamp.com/album/crossjoint-ep": {
    "url": "https://crossjointhc.bandcamp.com/album/crossjoint-ep",
    "title": "Crossjoint EP",
    "artist": "Crossjoint",
    "imageUrl": "https://f4.bcbits.com/img/a4041137169_16.jpg",
    "embedId": "3269608347"
  },
  "https://armouredangel.bandcamp.com/album/communion": "paid",
  "https://midnight-ohio.bandcamp.com/album/complete-and-total-hell": "paid",
  "https://acid-witch-detroit.bandcamp.com/album/witchtanic-hellucinations": "paid",
  "https://heroslastrite.bandcamp.com/album/wasted-prayer": "paid",
  "https://closedcasketactivities.bandcamp.com/album/gods-hate-mass-murder": "paid",
  "https://jpegmafia.bandcamp.com/album/black-ben-carson": {
    "url": "https://jpegmafia.bandcamp.com/album/black-ben-carson",
    "title": "Black Ben Carson",
    "artist": "JPEGMAFIA",
    "imageUrl": "https://f4.bcbits.com/img/a0926557137_16.jpg",
    "embedId": "1635612064"
  },
  "https://greatamericanghost.bandcamp.com/album/s-t-2013": "paid",
  "https://closedcasketactivities.bandcamp.com/album/amber-mote-in-the-black-vault": "paid",
  "https://candlelightrecordsuk.bandcamp.com/album/london": "paid",
  "https://thethirdeyerapists.bandcamp.com/album/magicians-of-the-holocaust": {
    "url": "https://thethirdeyerapists.bandcamp.com/album/magicians-of-the-holocaust",
    "title": "Magicians of the Holocaust",
    "artist": "The Third Eye Rapists",
    "imageUrl": "https://f4.bcbits.com/img/a0191387947_16.jpg",
    "embedId": "656235939"
  },
  "https://byzantine.bandcamp.com/album/to-release-is-to-resolve": "paid",
  "https://bindfl.bandcamp.com/album/true-colors": "paid",
  "https://byzantine.bandcamp.com/album/the-cicada-tree": "paid",
  "https://eruptionthrash.bandcamp.com/album/lifeless-paradise-2": "paid",
  "https://pedalstrike666.bandcamp.com/album/pedalstrike": {
    "url": "https://pedalstrike666.bandcamp.com/album/pedalstrike",
    "title": "pedalstrike.",
    "artist": "PEDALSTRIKE",
    "imageUrl": "https://f4.bcbits.com/img/a1997788118_16.jpg",
    "embedId": "648802682"
  },
  "https://borisrecords.bandcamp.com/album/s-t-7": "paid",
  "https://sidetracked.bandcamp.com/album/to-the-point-split": {
    "url": "https://sidetracked.bandcamp.com/album/to-the-point-split",
    "title": "To The Point split",
    "artist": "Sidetracked",
    "imageUrl": "https://f4.bcbits.com/img/a2371645133_16.jpg",
    "embedId": "1742068645"
  },
  "https://alexzelenka.bandcamp.com/album/phantoms": "paid",
  "https://elkofields.bandcamp.com/album/elko-fields": "paid",
  "https://armouredangel.bandcamp.com/album/wings-of-death": "paid",
  "https://thehell.bandcamp.com/album/youre-listening-to-the-hell": {
    "url": "https://thehell.bandcamp.com/album/youre-listening-to-the-hell",
    "title": "You're Listening To THE HELL",
    "artist": "THE HELL",
    "imageUrl": "https://f4.bcbits.com/img/a0338896587_16.jpg",
    "embedId": "4185349781"
  },
  "https://droidsattack.bandcamp.com/album/sci-fi-or-die": "paid",
  "https://expander.bandcamp.com/album/expander": {
    "url": "https://expander.bandcamp.com/album/expander",
    "title": "EXPANDER",
    "artist": "EXPANDER",
    "imageUrl": "https://f4.bcbits.com/img/a3960031441_16.jpg",
    "embedId": "3275518644"
  },
  "https://maniaxe.bandcamp.com/album/splatterthrash": "paid",
  "https://rebelyell.bandcamp.com/album/career-day": "paid",
  "https://archarus.bandcamp.com/album/thorr-axe-archarus-the-hobbit-split-album": "paid",
  "https://crim3s.bandcamp.com/album/crim3s-ep": "paid",
  "https://necronomikids.bandcamp.com/album/necronomikids": {
    "url": "https://necronomikids.bandcamp.com/album/necronomikids",
    "title": "Necronomikids",
    "artist": "Necronomikids",
    "imageUrl": "https://f4.bcbits.com/img/a0448370349_16.jpg",
    "embedId": "1039971321"
  },
  "https://borisrecords.bandcamp.com/album/premonition-ep-cassette": "paid",
  "https://gsf1992.bandcamp.com/album/the-los-santos-ep": "paid",
  "https://reclusenola.bandcamp.com/album/recluse": "paid",
  "https://zombieattackthrash.bandcamp.com/album/through-the-circles-of-hell": {
    "url": "https://zombieattackthrash.bandcamp.com/album/through-the-circles-of-hell",
    "title": "Through The Circles of Hell",
    "artist": "Zombie Attack",
    "imageUrl": "https://f4.bcbits.com/img/a4088990163_16.jpg",
    "embedId": "3935065677"
  },
  "https://sectxvx.bandcamp.com/album/sect": "paid",
  "https://sick-tired.bandcamp.com/album/split-12-w-sea-of-shit": {
    "url": "https://sick-tired.bandcamp.com/album/split-12-w-sea-of-shit",
    "title": "Split 12\" w/ Sea of Shit",
    "artist": "Sick/Tired",
    "imageUrl": "https://f4.bcbits.com/img/a1137940459_16.jpg",
    "embedId": "425713694"
  },
  "https://alexzelenka.bandcamp.com/album/burning-compilation-master-collection": "paid",
  "https://eruptionthrash.bandcamp.com/album/live-transmissions": "paid",
  "https://hellbringer.bandcamp.com/album/awakened-from-the-abyss": "paid",
  "https://borisrecords.bandcamp.com/album/sewer-metal-7": "paid",
  "https://ihaveaknife.bandcamp.com/album/of-criminals-and-kings": "paid",
  "https://trustissuespdx.bandcamp.com/album/finding-peace-in-the-darkness": "paid",
  "http://deathalizer.com/album/it-dwells-within": {
    "url": "http://deathalizer.com/album/it-dwells-within",
    "title": "It Dwells Within",
    "artist": "Deathalizer",
    "imageUrl": "http://f4.bcbits.com/img/a1781594491_16.jpg",
    "embedId": "584779844"
  },
  "https://moontoothny.bandcamp.com/album/freaks-ep": "paid",
  "https://fragileexistence.bandcamp.com/album/cataclysms-and-beginnings": "paid",
  "https://maniaxe.bandcamp.com/album/dungeon-bastards": "paid",
  "https://the-haunting-presence.bandcamp.com/album/2015-mlp": "paid",
  "https://teensuicide.bandcamp.com/album/i-will-be-my-own-hell-because-there-is-a-devil-inside-my-body": "paid",
  "https://nuke-detroit.bandcamp.com/album/nuke": "paid",
  "https://hellbringer.bandcamp.com/album/hellbringer": "paid",
  "https://disparoplayfast.bandcamp.com/album/hands-in-the-middle": "paid",
  "https://discourse1.bandcamp.com/album/1991-demo-25-year-anniversary-edition": "paid",
  "https://archarus.bandcamp.com/album/render-unto-archarus": "paid",
  "https://nooirax.bandcamp.com/album/lodo": "paid",
  "https://dressup69.bandcamp.com/album/self-titled": "paid",
  "https://crucified-mortals.bandcamp.com/album/psalms-of-the-dead-choir": "paid",
  "https://fuckyoupaymeclevo.bandcamp.com/album/fypm-various-songs": {
    "url": "https://fuckyoupaymeclevo.bandcamp.com/album/fypm-various-songs",
    "title": "FYPM various songs",
    "artist": "FYPM (Fuck You Pay Me*CLEVELAND*)",
    "imageUrl": "https://f4.bcbits.com/img/a2362309626_16.jpg",
    "embedId": "2983881909"
  },
  "https://thorr-axe.bandcamp.com/album/thorr-axe-archarus-the-hobbit-split": {
    "url": "https://thorr-axe.bandcamp.com/album/thorr-axe-archarus-the-hobbit-split",
    "title": "Thorr​-​Axe / Archarus - The Hobbit Split",
    "artist": "Thorr-Axe",
    "imageUrl": "https://f4.bcbits.com/img/a1959267515_16.jpg",
    "embedId": "1639757184"
  },
  "https://exdementia.bandcamp.com/album/crack-the-coffin": "paid",
  "https://resurrectionrecords.bandcamp.com/album/the-moonmaiden": {
    "url": "https://resurrectionrecords.bandcamp.com/album/the-moonmaiden",
    "title": "The Moonmaiden",
    "artist": "MDK",
    "imageUrl": "https://f4.bcbits.com/img/a3908798698_16.jpg",
    "embedId": "698696567"
  },
  "https://mizeryhardcore.bandcamp.com/album/survive-the-vibe-2": "paid",
  "https://closedcasketactivities.bandcamp.com/album/no-gods-no-masters": "paid",
  "https://blastasfuk.bandcamp.com/album/ultimate-whirlwind-of-incineration": "paid",
  "https://chemicide.bandcamp.com/album/the-act-of-retaliation": "paid",
  "https://necrofili.bandcamp.com/album/the-end-of-everything": "paid",
  "https://bonehunter-finland.bandcamp.com/album/sexual-panic-human-machine": "paid",
  "https://irishvoodoorecords.bandcamp.com/album/noncon": "paid",
  "https://blastasfuk.bandcamp.com/album/complete-mortality": "paid",
  "https://cultesdesghoules.bandcamp.com/album/spectres-over-transylvania": "paid",
  "https://saccage.bandcamp.com/album/death-crust-satanique-lp-cd-2012": "paid",
  "https://darkreverie.bandcamp.com/album/isis-lupus-brigit-ep": "paid",
  "https://septikonslaught.bandcamp.com/album/twitch-of-the-death-nerve": "paid",
  "https://deadheatca.bandcamp.com/album/access-denied-s-e-e-d": "paid",
  "https://gsf1992.bandcamp.com/album/the-las-venturas-ep": "paid",
  "https://hominidsounds.bandcamp.com/album/mister-lizard-7": "paid",
  "https://mutuallyassureddestruction.bandcamp.com/album/society": {
    "url": "https://mutuallyassureddestruction.bandcamp.com/album/society",
    "title": "Society",
    "artist": "Mutually Assured Destruction",
    "imageUrl": "https://f4.bcbits.com/img/a1314962044_16.jpg",
    "embedId": "282029835"
  },
  "https://foreseen.bandcamp.com/album/grave-danger": "paid",
  "https://escapefromthezoo.bandcamp.com/album/escape-from-the-zoo": "paid",
  "https://bat-richmond.bandcamp.com/album/wings-of-chains": "paid",
  "https://risingbeast.bandcamp.com/album/zhora": {
    "url": "https://risingbeast.bandcamp.com/album/zhora",
    "title": "Zhora",
    "artist": "MOONKNIGHT",
    "imageUrl": "https://f4.bcbits.com/img/a3187164711_16.jpg",
    "embedId": "2213954818"
  },
  "https://closedcasketactivities.bandcamp.com/album/call-it-war": "paid",
  "https://nylithia.bandcamp.com/album/hyperthrash": "paid",
  "https://metalwulf666.bandcamp.com/album/metalw-lf": "paid",
  "https://saccage.bandcamp.com/album/saccage-hellacaust-split-tape-7-2016": "paid",
  "https://pearstheband.bandcamp.com/album/green-star": "paid",
  "https://sidetracked.bandcamp.com/album/escape": {
    "url": "https://sidetracked.bandcamp.com/album/escape",
    "title": "Escape",
    "artist": "Sidetracked",
    "imageUrl": "https://f4.bcbits.com/img/a0793258496_16.jpg",
    "embedId": "871627133"
  },
  "https://osmoseproductions.bandcamp.com/album/nordjevel": "paid",
  "https://amken.bandcamp.com/album/theater-of-the-absurd": "paid",
  "https://escapefromthezoo.bandcamp.com/album/the-wasted-years-ep": "paid",
  "https://crim3s.bandcamp.com/album/stay-ugly-ep-2": "paid",
  "https://profanatica-us.bandcamp.com/album/disgusting-blasphemies-against-god": "paid",
  "https://eruptionthrash.bandcamp.com/album/tenses-collide-2": "paid",
  "https://momentumca.bandcamp.com/album/bliss": {
    "url": "https://momentumca.bandcamp.com/album/bliss",
    "title": "Bliss",
    "artist": "Momentum",
    "imageUrl": "https://f4.bcbits.com/img/a0672115671_16.jpg",
    "embedId": "320805946"
  },
  "https://speedrush.bandcamp.com/album/endless-war": "paid",
  "https://ikillya.bandcamp.com/album/war-for-an-idea": "paid",
  "https://closedcasketactivities.bandcamp.com/album/split-3": "paid",
  "https://cultesdesghoules.bandcamp.com/album/henbane": "paid",
  "https://terrifier-tym.bandcamp.com/album/weapons-of-thrash-destruction": "paid",
  "https://sidetracked.bandcamp.com/album/gods-america-split-cd": {
    "url": "https://sidetracked.bandcamp.com/album/gods-america-split-cd",
    "title": "God's America split cd",
    "artist": "Sidetracked",
    "imageUrl": "https://f4.bcbits.com/img/a1978068615_16.jpg",
    "embedId": "743219853"
  },
  "https://bestwishesrecords.bandcamp.com/album/bw03-impulse-to-destroy": {
    "url": "https://bestwishesrecords.bandcamp.com/album/bw03-impulse-to-destroy",
    "title": "BW03 - Impulse To Destroy",
    "artist": "Staunch",
    "imageUrl": "https://f4.bcbits.com/img/a3615758227_16.jpg",
    "embedId": "2953955892"
  },
  "https://panikk.bandcamp.com/album/unbearable-conditions-2nd-edition-metaltank": "paid",
  "https://sorceryhappens.bandcamp.com/album/piss-ripper": {
    "url": "https://sorceryhappens.bandcamp.com/album/piss-ripper",
    "title": "PISS RIPPER",
    "artist": "SORCERY",
    "imageUrl": "https://f4.bcbits.com/img/a2980650944_16.jpg",
    "embedId": "2545659056"
  },
  "http://music.lichkingmetal.com/album/the-omniclasm": "paid",
  "https://midnight-ohio.bandcamp.com/album/satanic-royalty": "paid",
  "https://relapsesampler.bandcamp.com/album/relapse-records-25-years-of-contamination": {
    "url": "https://relapsesampler.bandcamp.com/album/relapse-records-25-years-of-contamination",
    "title": "Relapse Records: 25 Years of Contamination",
    "artist": "Various Artists",
    "imageUrl": "https://f4.bcbits.com/img/a1163979296_16.jpg",
    "embedId": "2853377627"
  },
  "https://doubted208.bandcamp.com/album/reapers-grasp": {
    "url": "https://doubted208.bandcamp.com/album/reapers-grasp",
    "title": "Reaper's Grasp",
    "artist": "Doubted",
    "imageUrl": "https://f4.bcbits.com/img/a3157378170_16.jpg",
    "embedId": "2642667732"
  },
  "https://satanic-warmaster-finland.bandcamp.com/album/lux-satanae-thirteen-hymns-of-finnish-devil-worship": "paid",
  "https://extravasion.bandcamp.com/album/origins-of-magma-2": "paid",
  "https://horrific.bandcamp.com/album/your-worst-nightmare": "paid",
  "https://storiegrubb.bandcamp.com/album/the-invincible-allegory": {
    "url": "https://storiegrubb.bandcamp.com/album/the-invincible-allegory",
    "title": "The Invincible Allegory",
    "artist": "Storie Grubb",
    "imageUrl": "https://f4.bcbits.com/img/a0643977752_16.jpg",
    "embedId": "2237676061"
  },
  "https://cougardenband.bandcamp.com/album/keepondrifter": {
    "url": "https://cougardenband.bandcamp.com/album/keepondrifter",
    "title": "keepondrifter",
    "artist": "Cougar Den",
    "imageUrl": "https://f4.bcbits.com/img/a3007797099_16.jpg",
    "embedId": "1465030897"
  },
  "https://candlelightrecordsuk.bandcamp.com/album/antarctica": "paid",
  "https://silencermetal.bandcamp.com/album/the-great-bear": "paid",
  "https://heavenandhellrecords.bandcamp.com/album/free-digital-download-live-at-fargos": {
    "url": "https://heavenandhellrecords.bandcamp.com/album/free-digital-download-live-at-fargos",
    "title": "FREE digital download: Live at Fargo's",
    "artist": "DENIAL",
    "imageUrl": "https://f4.bcbits.com/img/a0434117834_16.jpg",
    "embedId": "1378678311"
  },
  "https://mursa.bandcamp.com/album/mrsa": {
    "url": "https://mursa.bandcamp.com/album/mrsa",
    "title": "MRSA",
    "artist": "Mursa",
    "imageUrl": "https://f4.bcbits.com/img/a2574471404_16.jpg",
    "embedId": "973108286"
  },
  "https://osmoseproductions.bandcamp.com/album/the-minds-i": "paid",
  "https://tallteetapes.bandcamp.com/album/demo-2015": {
    "url": "https://tallteetapes.bandcamp.com/album/demo-2015",
    "title": "Demo 2015",
    "artist": "Pillars",
    "imageUrl": "https://f4.bcbits.com/img/a1116982002_16.jpg",
    "embedId": "616657605"
  },
  "https://toxicholocaust.bandcamp.com/album/conjure-and-command-deluxe-edition": "paid",
  "https://allagash.bandcamp.com/album/allagash": "paid",
  "https://mindforceny.bandcamp.com/album/the-future-of": "paid",
  "https://steed2.bandcamp.com/album/surrounded-by-cowards": "paid",
  "https://witheria.bandcamp.com/album/infinite-recollection": "paid",
  "https://imperialmindengineering.bandcamp.com/album/cognizant-lp": "paid",
  "https://pestifere.bandcamp.com/album/hope-misery-death": "paid",
  "https://saccage.bandcamp.com/album/vorace-mcd-7-2014": "paid",
  "https://allouthelter.bandcamp.com/album/ruins": "paid",
  "https://speedstab.bandcamp.com/album/immortal-affliction-ep": "paid",
  "https://razorband.bandcamp.com/album/shotgun-justice-reissue": "paid",
  "https://firstplacescienceproject.bandcamp.com/album/fpsp-wrecks": {
    "url": "https://firstplacescienceproject.bandcamp.com/album/fpsp-wrecks",
    "title": "FPSP​.​WRECKS",
    "artist": "First Place Science Project",
    "imageUrl": "https://f4.bcbits.com/img/a3401628414_16.jpg",
    "embedId": "3546914556"
  },
  "https://a-shower-eh-cunts.bandcamp.com/album/hunt-the-cunts-ep": {
    "url": "https://a-shower-eh-cunts.bandcamp.com/album/hunt-the-cunts-ep",
    "title": "Hunt The Cunts EP",
    "artist": "A Shower Eh Cunts",
    "imageUrl": "https://f4.bcbits.com/img/a0547404279_16.jpg",
    "embedId": "276065475"
  },
  "https://dishammer.bandcamp.com/album/vintage-addiction": "paid",
  "https://borisrecords.bandcamp.com/album/kneel-before-none": "paid",
  "https://hirs.bandcamp.com/album/comps-etc": {
    "url": "https://hirs.bandcamp.com/album/comps-etc",
    "title": "Comps etc",
    "artist": "HIRS",
    "imageUrl": "https://f4.bcbits.com/img/a2299576970_16.jpg",
    "embedId": "3550537542"
  },
  "https://speedwolf-us.bandcamp.com/album/ride-with-death": "paid",
  "https://hirs.bandcamp.com/album/the-second-100-songs-2": {
    "url": "https://hirs.bandcamp.com/album/the-second-100-songs-2",
    "title": "THE SECOND 100 SONGS",
    "artist": "HIRS",
    "imageUrl": "https://f4.bcbits.com/img/a2748284391_16.jpg",
    "embedId": "192450134"
  },
  "https://aminals.bandcamp.com/album/dead-air": {
    "url": "https://aminals.bandcamp.com/album/dead-air",
    "title": "DEAD AIR",
    "artist": "Aminals",
    "imageUrl": "https://f4.bcbits.com/img/a0630372297_16.jpg",
    "embedId": "2521290010"
  },
  "https://9heart.bandcamp.com/album/dantesdmg-2-ep-2016": {
    "url": "https://9heart.bandcamp.com/album/dantesdmg-2-ep-2016",
    "title": "DANTESDMG 2 EP (2016)",
    "artist": "9-Heart // DantesDMG",
    "imageUrl": "https://f4.bcbits.com/img/a0680251997_16.jpg",
    "embedId": "3146238798"
  },
  "https://sidetracked.bandcamp.com/album/annihilation-doctrine": {
    "url": "https://sidetracked.bandcamp.com/album/annihilation-doctrine",
    "title": "Annihilation Doctrine",
    "artist": "Sidetracked",
    "imageUrl": "https://f4.bcbits.com/img/a1405122401_16.jpg",
    "embedId": "2531055405"
  },
  "https://sidetracked.bandcamp.com/album/ammunition": {
    "url": "https://sidetracked.bandcamp.com/album/ammunition",
    "title": "Ammunition",
    "artist": "Sidetracked",
    "imageUrl": "https://f4.bcbits.com/img/a2456651379_16.jpg",
    "embedId": "880220042"
  },
  "https://sidetracked.bandcamp.com/album/abandon": {
    "url": "https://sidetracked.bandcamp.com/album/abandon",
    "title": "Abandon",
    "artist": "Sidetracked",
    "imageUrl": "https://f4.bcbits.com/img/a0685400372_16.jpg",
    "embedId": "1607536847"
  },
  "https://sidetracked.bandcamp.com/album/final-curtain": {
    "url": "https://sidetracked.bandcamp.com/album/final-curtain",
    "title": "Final Curtain",
    "artist": "Sidetracked",
    "imageUrl": "https://f4.bcbits.com/img/a1996526257_16.jpg",
    "embedId": "636970568"
  },
  "https://sidetracked.bandcamp.com/album/pillars": {
    "url": "https://sidetracked.bandcamp.com/album/pillars",
    "title": "Pillars",
    "artist": "Sidetracked",
    "imageUrl": "https://f4.bcbits.com/img/a2152133608_16.jpg",
    "embedId": "2454811527"
  },
  "https://judiciarytx.bandcamp.com/album/the-axis-of-equality": "paid",
  "https://sidetracked.bandcamp.com/album/emerge-unscathed": {
    "url": "https://sidetracked.bandcamp.com/album/emerge-unscathed",
    "title": "Emerge Unscathed",
    "artist": "Sidetracked",
    "imageUrl": "https://f4.bcbits.com/img/a1377393775_16.jpg",
    "embedId": "3127313427"
  },
  "https://mindforceny.bandcamp.com/album/2016-demo": "paid",
  "https://candlelightrecordsuk.bandcamp.com/album/angl": "paid",
  "https://prcmusic.bandcamp.com/album/gorelust-we-are-the-undead-cd": "paid",
  "https://deadheatca.bandcamp.com/album/s-t": "paid",
  "https://hirs.bandcamp.com/album/magical-wanderful": {
    "url": "https://hirs.bandcamp.com/album/magical-wanderful",
    "title": "MAGICal​/​WANDerful",
    "artist": "HIRS",
    "imageUrl": "https://f4.bcbits.com/img/a3722139815_16.jpg",
    "embedId": "365890493"
  },
  "https://deathsgrip.bandcamp.com/album/views-from-my-deathbed": {
    "url": "https://deathsgrip.bandcamp.com/album/views-from-my-deathbed",
    "title": "Views From My Deathbed",
    "artist": "Deathbed",
    "imageUrl": "https://f4.bcbits.com/img/a0533463718_16.jpg",
    "embedId": "261540839"
  },
  "https://vnkv.bandcamp.com/album/-": "paid",
  "https://vnkv.bandcamp.com/album/5772": "paid",
  "https://deathhammer.bandcamp.com/album/phantom-knights": "paid",
  "https://witchtrap.bandcamp.com/album/trap-the-witch-3": "paid",
  "https://risingbeast.bandcamp.com/album/valinor": {
    "url": "https://risingbeast.bandcamp.com/album/valinor",
    "title": "Valinor",
    "artist": "MOONKNIGHT",
    "imageUrl": "https://f4.bcbits.com/img/a0224188122_16.jpg",
    "embedId": "228842518"
  },
  "https://mursa.bandcamp.com/album/ectopic": {
    "url": "https://mursa.bandcamp.com/album/ectopic",
    "title": "Ectopic",
    "artist": "Mursa",
    "imageUrl": "https://f4.bcbits.com/img/a3065287220_16.jpg",
    "embedId": "4064189241"
  },
  "https://clownsband.bandcamp.com/album/im-not-right": "paid",
  "https://castet.bandcamp.com/album/punk-side-of-the-moon": "paid",
  "https://eightsins.bandcamp.com/album/world-of-sorrow": "paid",
  "https://begrimeexemious.bandcamp.com/album/split-7-w-flash-out": {
    "url": "https://begrimeexemious.bandcamp.com/album/split-7-w-flash-out",
    "title": "Split 7\" w/ Flash Out",
    "artist": "Begrime Exemious",
    "imageUrl": "https://f4.bcbits.com/img/a2373454876_16.jpg",
    "embedId": "3737862435"
  },
  "https://cellphonesband.bandcamp.com/album/its-halloween-a-haunted-house-soundtrack": "paid",
  "https://comeandgetit69.bandcamp.com/album/basement-ep": {
    "url": "https://comeandgetit69.bandcamp.com/album/basement-ep",
    "title": "Basement Ep",
    "artist": "Come And Get It",
    "imageUrl": "https://f4.bcbits.com/img/a2602263564_16.jpg",
    "embedId": "3151753019"
  },
  "https://candlelightrecordsuk.bandcamp.com/album/echoes-and-cinder": "paid",
  "https://begrimeexemious.bandcamp.com/album/set-ablaze-the-kingdom-of-abraham": {
    "url": "https://begrimeexemious.bandcamp.com/album/set-ablaze-the-kingdom-of-abraham",
    "title": "Set Ablaze The Kingdom of Abraham",
    "artist": "Begrime Exemious",
    "imageUrl": "https://f4.bcbits.com/img/a2908459410_16.jpg",
    "embedId": "2208921520"
  },
  "https://cemeterypiss.bandcamp.com/album/such-the-vultures-love-7": {
    "url": "https://cemeterypiss.bandcamp.com/album/such-the-vultures-love-7",
    "title": "Such The Vultures Love 7\"",
    "artist": "Cemetery Piss",
    "imageUrl": "https://f4.bcbits.com/img/a1699368879_16.jpg",
    "embedId": "2574853742"
  },
  "https://castet.bandcamp.com/album/nie-graj-z-nami-w-chuja": "paid",
  "https://cellphonesband.bandcamp.com/album/hospital-spaceship-ep": "paid",
  "https://horseburner.bandcamp.com/album/dirt-city": {
    "url": "https://horseburner.bandcamp.com/album/dirt-city",
    "title": "Dirt City",
    "artist": "Horseburner",
    "imageUrl": "https://f4.bcbits.com/img/a1106100502_16.jpg",
    "embedId": "1924423570"
  },
  "https://cellphonesband.bandcamp.com/album/argyle-ep": "paid",
  "https://blood-feast.bandcamp.com/album/the-future-state-of-wicked": "paid",
  "https://candlelightrecordsuk.bandcamp.com/album/ix-equilibrium": "paid",
  "https://gorcrow.bandcamp.com/album/ii": {
    "url": "https://gorcrow.bandcamp.com/album/ii",
    "title": "II",
    "artist": "Gorcrow",
    "imageUrl": "https://f4.bcbits.com/img/a0747986392_16.jpg",
    "embedId": "3700000698"
  },
  "https://comeandgetit69.bandcamp.com/album/cvm-of-possesion": {
    "url": "https://comeandgetit69.bandcamp.com/album/cvm-of-possesion",
    "title": "CVM OF POSSESION",
    "artist": "Come And Get It",
    "imageUrl": "https://f4.bcbits.com/img/a1533614866_16.jpg",
    "embedId": "4214240373"
  },
  "https://castet.bandcamp.com/album/kings-of-punk": "paid",
  "https://comeandgetit69.bandcamp.com/album/thanatron": "paid",
  "https://deiphago-philippines.bandcamp.com/album/satan-alpha-omega": "paid",
  "https://eightsins.bandcamp.com/album/serpents": "paid",
  "https://cellphonesband.bandcamp.com/album/get-you-alone": "paid",
  "https://throwingbricks604.bandcamp.com/album/demo-2": {
    "url": "https://throwingbricks604.bandcamp.com/album/demo-2",
    "title": "Demo",
    "artist": "Throwing Bricks",
    "imageUrl": "https://f4.bcbits.com/img/a1667480301_16.jpg",
    "embedId": "2196701211"
  },
  "https://candlelightrecordsuk.bandcamp.com/album/darkness-died-today": "paid",
  "https://fordtheatrereunion.bandcamp.com/album/legends-landmarks": "paid",
  "https://hirs.bandcamp.com/album/y-u-cant-kill-us": {
    "url": "https://hirs.bandcamp.com/album/y-u-cant-kill-us",
    "title": "YØU CAN'T KILL US",
    "artist": "HIRS",
    "imageUrl": "https://f4.bcbits.com/img/a3121692056_16.jpg",
    "embedId": "3924332647"
  },
  "https://toxikwaltz.bandcamp.com/album/declassified": "paid",
  "https://skullcrackhc.bandcamp.com/album/cut-it-down": "paid",
  "https://absu.bandcamp.com/album/tara": "paid",
  "https://tempestuous.bandcamp.com/album/born-into-these-waters": "paid",
  "https://osmoseproductions.bandcamp.com/album/purity": "paid",
  "https://bindfl.bandcamp.com/album/2016-promo": "paid",
  "https://warcursemetal.bandcamp.com/album/final-days": "paid",
  "https://candlelightrecordsuk.bandcamp.com/album/in-the-halls-of-awaiting": "paid",
  "https://osmoseproductions.bandcamp.com/album/panzer-division-marduk": "paid",
  "http://music.lichkingmetal.com/album/born-of-the-bomb-2": "paid",
  "https://knightoftheround.bandcamp.com/album/fates-delusion": {
    "url": "https://knightoftheround.bandcamp.com/album/fates-delusion",
    "title": "Fate's Delusion",
    "artist": "Knight of the Round",
    "imageUrl": "https://f4.bcbits.com/img/a1215584580_16.jpg",
    "embedId": "248672658"
  },
  "https://candlelightrecordsuk.bandcamp.com/album/since-the-day-it-all-came-down": "paid",
  "https://deathhammer.bandcamp.com/album/onward-to-the-pits": "paid",
  "https://knightoftheround.bandcamp.com/album/gaias-bane": {
    "url": "https://knightoftheround.bandcamp.com/album/gaias-bane",
    "title": "Gaia's Bane",
    "artist": "Knight of the Round",
    "imageUrl": "https://f4.bcbits.com/img/a3860654040_16.jpg",
    "embedId": "3140801217"
  },
  "https://candlelightrecordsuk.bandcamp.com/album/kyrr": "paid",
  "https://ironlungpv.bandcamp.com/album/life-iron-lung-death-lp-cd-lungs-069": "paid",
  "https://candlelightrecordsuk.bandcamp.com/album/above-the-weeping-world": "paid",
  "https://dejadeathband.bandcamp.com/album/satan-is-losing-momentum": {
    "url": "https://dejadeathband.bandcamp.com/album/satan-is-losing-momentum",
    "title": "Satan Is Losing Momentum",
    "artist": "Dejadeath",
    "imageUrl": "https://f4.bcbits.com/img/a2196500627_16.jpg",
    "embedId": "3427260629"
  },
  "https://selfharm780.bandcamp.com/album/xv": {
    "url": "https://selfharm780.bandcamp.com/album/xv",
    "title": "XV",
    "artist": "Self Harm",
    "imageUrl": "https://f4.bcbits.com/img/a3174285581_16.jpg",
    "embedId": "2240593775"
  },
  "https://rehashed.bandcamp.com/album/government-cheese-2": "paid",
  "https://shed-the-skin.bandcamp.com/album/harrowing-faith": "paid",
  "https://cellphonesband.bandcamp.com/album/no": "paid",
  "https://castet.bandcamp.com/album/twardsi-ni-najtwardsza-garda": "paid",
  "https://eightsins.bandcamp.com/album/blood-of-revenge": "paid",
  "https://eightsins.bandcamp.com/album/straight-hate": "paid",
  "https://toxicwizard.bandcamp.com/album/total-destruction-aka-vs": {
    "url": "https://toxicwizard.bandcamp.com/album/total-destruction-aka-vs",
    "title": "Total Destruction aka 岡田 vs オメガ",
    "artist": "Toxic Wizard 有毒なウィザード",
    "imageUrl": "https://f4.bcbits.com/img/a2807373090_16.jpg",
    "embedId": "3676368695"
  },
  "https://candlelightrecordsuk.bandcamp.com/album/across-the-dark": "paid",
  "https://nowheresongs.bandcamp.com/album/virtual-reality-future-suit": "paid",
  "https://kickstandrecords.bandcamp.com/album/throwin-grunge-in-yer-face": {
    "url": "https://kickstandrecords.bandcamp.com/album/throwin-grunge-in-yer-face",
    "title": "Throwin' Grunge In Yer' Face",
    "artist": "Various Artists for donations download, all proceeds go to St. Judes Hospital for children",
    "imageUrl": "https://f4.bcbits.com/img/a2146911468_16.jpg",
    "embedId": "1715133235"
  },
  "https://propagandhi.bandcamp.com/album/live-from-occupied-territory-an-official-bootleg": "paid",
  "https://candlelightrecordsuk.bandcamp.com/album/in-the-nightside-eclipse-20th-anniversary-remastered-edition": "paid",
  "https://propagandhi.bandcamp.com/album/the-supporting-caste-demos": "paid",
  "https://hellobastards.bandcamp.com/album/hello-bastards-lp-2014-full-album": "paid",
  "https://skulled.bandcamp.com/album/eat-thrash-2": "paid",
  "https://horndal.bandcamp.com/album/horndal": "paid",
  "https://clownsband.bandcamp.com/album/bad-blood-2": "paid",
  "https://blasthrash.bandcamp.com/album/violence-just-for-fun": "paid",
  "https://candlelightrecordsuk.bandcamp.com/album/pandoras-pinata": "paid",
  "https://black-death.bandcamp.com/album/black-death": "paid",
  "https://weaponizer.bandcamp.com/album/weap-nizer-self-titled-debut-remastered-2012": "paid",
  "https://nobodyridesforfree.bandcamp.com/album/z28": "paid",
  "https://closedcasketactivities.bandcamp.com/album/diablo-con-amor-adios": "paid",
  "https://moontoothny.bandcamp.com/album/chromaparagon": "paid",
  "https://ar-15nola.bandcamp.com/album/dogs-of-war": "paid",
  "https://midnight-ohio.bandcamp.com/album/no-mercy-for-mayhem": "paid",
  "https://runningdeath.bandcamp.com/album/dressage": "paid",
  "https://prank.bandcamp.com/album/lifes-blood-hardcore-a-d-1988": "paid",
  "https://pearstheband.bandcamp.com/album/go-to-prison-3": "paid",
  "https://perversor.bandcamp.com/album/anticosmocrator": "paid",
  "https://pokerfacerus.bandcamp.com/album/game-on": "paid",
  "https://satanarchist.bandcamp.com/album/first-against-the-wall": "paid",
  "https://bareteethmusic.bandcamp.com/album/first-the-town-then-the-world": "paid",
  "https://exmortus-official.bandcamp.com/album/ride-forth": "paid",
  "https://begrimeexemious.bandcamp.com/album/visions-of-the-scourge": {
    "url": "https://begrimeexemious.bandcamp.com/album/visions-of-the-scourge",
    "title": "Visions of the Scourge",
    "artist": "Begrime Exemious",
    "imageUrl": "https://f4.bcbits.com/img/a1121642648_16.jpg",
    "embedId": "1295386143"
  },
  "https://nobodyridesforfree.bandcamp.com/album/space-bastard-single": "paid",
  "https://nemesisnc.bandcamp.com/album/atrocity-unleashed": "paid",
  "https://communityrecords.bandcamp.com/album/stuck-lucky": "paid",
  "https://gsf1992.bandcamp.com/album/vol-10": {
    "url": "https://gsf1992.bandcamp.com/album/vol-10",
    "title": "VOL. 1​.​0",
    "artist": "Grove Street Families",
    "imageUrl": "https://f4.bcbits.com/img/a2689647826_16.jpg",
    "embedId": "798501626"
  },
  "https://ratsofrealityband.bandcamp.com/album/the-art-of-debilitation-ep": {
    "url": "https://ratsofrealityband.bandcamp.com/album/the-art-of-debilitation-ep",
    "title": "The Art of Debilitation EP",
    "artist": "Rats of Reality",
    "imageUrl": "https://f4.bcbits.com/img/a0235895151_16.jpg",
    "embedId": "4116529639"
  },
  "https://pizzatramp.bandcamp.com/album/blowing-chunks": "paid",
  "https://pizzatramp.bandcamp.com/album/war-or-nothing": "paid",
  "https://pizzatramp.bandcamp.com/album/two-quid-ten-minutes": {
    "url": "https://pizzatramp.bandcamp.com/album/two-quid-ten-minutes",
    "title": "Two Quid Ten Minutes",
    "artist": "Pizzatramp",
    "imageUrl": "https://f4.bcbits.com/img/a1959362177_16.jpg",
    "embedId": "1691826419"
  },
  "https://backswing.bandcamp.com/album/sos": "paid",
  "https://paladinatl.bandcamp.com/album/demo-2017": {
    "url": "https://paladinatl.bandcamp.com/album/demo-2017",
    "title": "Demo 2017",
    "artist": "Paladin",
    "imageUrl": "https://f4.bcbits.com/img/a3011234493_16.jpg",
    "embedId": "1344490377"
  },
  "https://escapefromthezoo.bandcamp.com/album/killacopter": {
    "url": "https://escapefromthezoo.bandcamp.com/album/killacopter",
    "title": "KILLACOPTER",
    "artist": "Escape from the ZOO",
    "imageUrl": "https://f4.bcbits.com/img/a1497550898_16.jpg",
    "embedId": "4193168527"
  },
  "https://pizzatramp.bandcamp.com/album/late-night-at-nettys": "paid",
  "https://skullcrackhc.bandcamp.com/album/full-blast": "paid",
  "https://clownsband.bandcamp.com/album/lucid-again": "paid",
  "https://closedcasketactivities.bandcamp.com/album/thousand-mile-stare": "paid",
  "https://facerip.bandcamp.com/album/radioactive-race": "paid",
  "https://joelgrind.bandcamp.com/album/the-yellowgoat-sessions": {
    "url": "https://joelgrind.bandcamp.com/album/the-yellowgoat-sessions",
    "title": "The YELLOWGOAT Sessions",
    "artist": "Joel Grind",
    "imageUrl": "https://f4.bcbits.com/img/a3024196332_16.jpg",
    "embedId": "1596929003"
  },
  "https://buildingsband.bandcamp.com/album/melt-cry-sleep": "paid",
  "https://kwadraciokrecords.bandcamp.com/album/various-artist-za-kr-tko-za-szybko-compilation": "paid",
  "https://risingbeast.bandcamp.com/album/the-shores-of-space": {
    "url": "https://risingbeast.bandcamp.com/album/the-shores-of-space",
    "title": "The Shores of Space",
    "artist": "DARGAR",
    "imageUrl": "https://f4.bcbits.com/img/a1494525469_16.jpg",
    "embedId": "3786684118"
  },
  "https://numbskulls.bandcamp.com/album/pizza-box": {
    "url": "https://numbskulls.bandcamp.com/album/pizza-box",
    "title": "Pizza Box",
    "artist": "Numbskulls",
    "imageUrl": "https://f4.bcbits.com/img/a4109172285_16.jpg",
    "embedId": "2598306885"
  },
  "https://sick-tired.bandcamp.com/album/king-of-dirt-12-lp": {
    "url": "https://sick-tired.bandcamp.com/album/king-of-dirt-12-lp",
    "title": "King of Dirt - 12\" LP",
    "artist": "Sick/Tired",
    "imageUrl": "https://f4.bcbits.com/img/a4062605626_16.jpg",
    "embedId": "2618469619"
  },
  "https://inhumanformlowell.bandcamp.com/album/earthen-urn-2": {
    "url": "https://inhumanformlowell.bandcamp.com/album/earthen-urn-2",
    "title": "Earthen Urn",
    "artist": "In Human Form (IHF)",
    "imageUrl": "https://f4.bcbits.com/img/a1576009574_16.jpg",
    "embedId": "3973453304"
  },
  "https://numbskulls.bandcamp.com/album/heads-in-the-sand": {
    "url": "https://numbskulls.bandcamp.com/album/heads-in-the-sand",
    "title": "Heads In The Sand",
    "artist": "Numbskulls",
    "imageUrl": "https://f4.bcbits.com/img/a2133348209_16.jpg",
    "embedId": "2846530891"
  },
  "https://numbskulls.bandcamp.com/album/leader-meredith-mcarthur": {
    "url": "https://numbskulls.bandcamp.com/album/leader-meredith-mcarthur",
    "title": "Leader - Meredith - McArthur",
    "artist": "Numbskulls",
    "imageUrl": "https://f4.bcbits.com/img/a3629439469_16.jpg",
    "embedId": "2493243611"
  },
  "https://victimizer.bandcamp.com/album/rapid-thrashing-violence": "paid",
  "https://thewesharedmilk.bandcamp.com/album/lame-sunset-2": "paid",
  "https://leashnh.bandcamp.com/album/dead-end-breed": {
    "url": "https://leashnh.bandcamp.com/album/dead-end-breed",
    "title": "Dead End Breed",
    "artist": "LEASH",
    "imageUrl": "https://f4.bcbits.com/img/a3692638213_16.jpg",
    "embedId": "601981559"
  },
  "https://saveyourgenerationrecords.bandcamp.com/album/time-heals-all-wounds-syg-015": {
    "url": "https://saveyourgenerationrecords.bandcamp.com/album/time-heals-all-wounds-syg-015",
    "title": "Time Heals All Wounds (SYG​-​015)",
    "artist": "The Most Dangerous Animal",
    "imageUrl": "https://f4.bcbits.com/img/a1458052827_16.jpg",
    "embedId": "3835117552"
  },
  "https://strafplanet.bandcamp.com/album/tape": "paid",
  "https://osmoseproductions.bandcamp.com/album/new-obscurantis-order": "paid",
  "https://propagandhi.bandcamp.com/album/supporting-caste": "paid",
  "https://illegalbodies.bandcamp.com/album/mindflayers": "paid",
  "https://blastasfuk.bandcamp.com/album/agonizing-pain-and-perpetual-misery": "paid",
  "https://candlelightrecordsuk.bandcamp.com/album/the-butchers-ballroom": "paid",
  "https://dealeroakland.bandcamp.com/album/billionaire-boys-club": "paid",
  "https://brokenboneshc.bandcamp.com/album/dead-gone-e-p": "paid",
  "https://iothardcore.bandcamp.com/album/instruments-of-torture": {
    "url": "https://iothardcore.bandcamp.com/album/instruments-of-torture",
    "title": "Instruments of torture",
    "artist": "Instruments of torture",
    "imageUrl": "https://f4.bcbits.com/img/a2200475626_16.jpg",
    "embedId": "4062221810"
  }
}
